[
  {
    "id": 1,
    "type": "dump_truck",
    "name": "Самосвал КамАЗ-6522 №01",
    "home_type": "parking",
    "home_id": 1,
    "coords": [56.564175, 36.44286],
    "speed_kmh": 0,
    "current_task": "Ожидание рейса с битумом",
    "location_type": "parking",
    "location_name": "Стоянка №1",
    "schedule": [
      {"date": "2026-05-18", "time": "08:00", "location": "Стоянка №1", "task": "Выдвижение на АБЗ"},
      {"date": "2026-05-18", "time": "09:15", "location": "АБЗ Высоковский", "task": "Загрузка асфальтобетона"},
      {"date": "2026-05-18", "time": "10:00", "location": "Участок км 45", "task": "Разгрузка материала"},
      {"date": "2026-05-18", "time": "10:30", "location": "АБЗ Высоковский", "task": "Обратный рейс — загрузка"},
      {"date": "2026-05-18", "time": "11:15", "location": "Участок км 45", "task": "Разгрузка материала"},
      {"date": "2026-05-18", "time": "14:00", "location": "Стоянка №1", "task": "Конец смены"}
    ]
  },
  {
    "id": 2,
    "type": "dump_truck",
    "name": "Самосвал КамАЗ-6522 №02",
    "home_type": "parking",
    "home_id": 1,
    "coords": [56.564175, 36.44286],
    "speed_kmh": 0,
    "current_task": "Плановое ТО",
    "location_type": "parking",
    "location_name": "Стоянка №1",
    "schedule": [
      {"date": "2026-05-18", "time": "08:00", "location": "Стоянка №1", "task": "Плановое техническое обслуживание"},
      {"date": "2026-05-18", "time": "13:00", "location": "Стоянка №1", "task": "Готовность к рейсу"},
      {"date": "2026-05-18", "time": "13:30", "location": "АБЗ Высоковский", "task": "Загрузка асфальтобетона"},
      {"date": "2026-05-18", "time": "14:15", "location": "Участок км 78", "task": "Разгрузка материала"}
    ]
  },
  {
    "id": 3,
    "type": "transfer_machine",
    "name": "Перегружатель Roadtec SB-2500 №1",
    "home_type": "site",
    "home_id": "road-01",
    "coords": [56.390318, 36.571799],
    "speed_kmh": 0,
    "current_task": "Перегрузка смеси в укладчик",
    "location_type": "site",
    "location_name": "Участок М-11 км 45",
    "schedule": [
      {"date": "2026-05-18", "time": "08:00", "location": "Участок км 45", "task": "Подготовка оборудования"},
      {"date": "2026-05-18", "time": "08:30", "location": "Участок км 45", "task": "Начало перегрузки смеси"},
      {"date": "2026-05-18", "time": "12:00", "location": "Участок км 45", "task": "Перерыв"},
      {"date": "2026-05-18", "time": "13:00", "location": "Участок км 45", "task": "Продолжение перегрузки"},
      {"date": "2026-05-18", "time": "17:00", "location": "Участок км 45", "task": "Конец смены"}
    ]
  },
  {
    "id": 4,
    "type": "paver",
    "name": "Асфальтоукладчик Vogele Super 1900-3 №1",
    "home_type": "site",
    "home_id": "road-01",
    "coords": [56.390318, 36.571799],
    "speed_kmh": 0,
    "current_task": "Укладка асфальтобетона",
    "location_type": "site",
    "location_name": "Участок М-11 км 45",
    "schedule": [
      {"date": "2026-05-18", "time": "08:00", "location": "Участок км 45", "task": "Прогрев и настройка"},
      {"date": "2026-05-18", "time": "08:30", "location": "Участок км 45", "task": "Укладка покрытия"},
      {"date": "2026-05-18", "time": "12:00", "location": "Участок км 45", "task": "Технологический перерыв"},
      {"date": "2026-05-18", "time": "13:00", "location": "Участок км 45", "task": "Укладка покрытия"},
      {"date": "2026-05-18", "time": "17:00", "location": "Участок км 45", "task": "Конец смены"}
    ]
  },
  {
    "id": 5,
    "type": "roller",
    "name": "Каток HAMM HD+ 120i №1",
    "home_type": "site",
    "home_id": "road-01",
    "coords": [56.390318, 36.571799],
    "speed_kmh": 0,
    "current_task": "Уплотнение покрытия",
    "location_type": "site",
    "location_name": "Участок М-11 км 45",
    "schedule": [
      {"date": "2026-05-18", "time": "08:30", "location": "Участок км 45", "task": "Уплотнение первичного слоя"},
      {"date": "2026-05-18", "time": "12:00", "location": "Участок км 45", "task": "Технологический перерыв"},
      {"date": "2026-05-18", "time": "13:00", "location": "Участок км 45", "task": "Уплотнение финишного слоя"},
      {"date": "2026-05-18", "time": "17:00", "location": "Участок км 45", "task": "Конец смены"}
    ]
  },
  {
    "id": 6,
    "type": "dump_truck",
    "name": "Самосвал МАЗ-6516 №01",
    "home_type": "parking",
    "home_id": 2,
    "coords": [57.240149, 34.899585],
    "speed_kmh": 0,
    "current_task": "Ожидание рейса с битумом",
    "location_type": "parking",
    "location_name": "Стоянка №2",
    "schedule": [
      {"date": "2026-05-18", "time": "08:00", "location": "Стоянка №2", "task": "Выдвижение на АБЗ"},
      {"date": "2026-05-18", "time": "09:00", "location": "АБЗ №1, Тверская", "task": "Загрузка асфальтобетона"},
      {"date": "2026-05-18", "time": "10:30", "location": "Участок км 148", "task": "Разгрузка материала"},
      {"date": "2026-05-18", "time": "11:30", "location": "АБЗ №1, Тверская", "task": "Обратный рейс — загрузка"},
      {"date": "2026-05-18", "time": "13:00", "location": "Участок км 148", "task": "Разгрузка материала"},
      {"date": "2026-05-18", "time": "16:00", "location": "Стоянка №2", "task": "Конец смены"}
    ]
  },
  {
    "id": 7,
    "type": "dump_truck",
    "name": "Самосвал МАЗ-6516 №02",
    "home_type": "parking",
    "home_id": 2,
    "coords": [57.240149, 34.899585],
    "speed_kmh": 0,
    "current_task": "Готовность к рейсу",
    "location_type": "parking",
    "location_name": "Стоянка №2",
    "schedule": [
      {"date": "2026-05-18", "time": "09:00", "location": "Стоянка №2", "task": "Выдвижение на АБЗ"},
      {"date": "2026-05-18", "time": "10:00", "location": "АБЗ №1, Тверская", "task": "Загрузка асфальтобетона"},
      {"date": "2026-05-18", "time": "11:30", "location": "Участок км 193", "task": "Разгрузка материала"},
      {"date": "2026-05-18", "time": "13:00", "location": "АБЗ №1, Тверская", "task": "Погрузка"},
      {"date": "2026-05-18", "time": "14:30", "location": "Участок км 193", "task": "Разгрузка"},
      {"date": "2026-05-18", "time": "16:00", "location": "Стоянка №2", "task": "Конец смены"}
    ]
  },
  {
    "id": 8,
    "type": "transfer_machine",
    "name": "Перегружатель Roadtec SB-2500 №2",
    "home_type": "site",
    "home_id": "road-03",
    "coords": [56.761401, 36.207698],
    "speed_kmh": 0,
    "current_task": "Подготовка к работе",
    "location_type": "site",
    "location_name": "Участок М-11 км 112",
    "schedule": [
      {"date": "2026-05-18", "time": "09:00", "location": "Участок км 112", "task": "Подготовка оборудования"},
      {"date": "2026-05-18", "time": "09:30", "location": "Участок км 112", "task": "Начало перегрузки смеси"},
      {"date": "2026-05-18", "time": "13:00", "location": "Участок км 112", "task": "Перерыв"},
      {"date": "2026-05-18", "time": "14:00", "location": "Участок км 112", "task": "Продолжение перегрузки"},
      {"date": "2026-05-18", "time": "17:00", "location": "Участок км 112", "task": "Конец смены"}
    ]
  },
  {
    "id": 9,
    "type": "paver",
    "name": "Асфальтоукладчик Vogele Super 1900-3 №2",
    "home_type": "site",
    "home_id": "road-02",
    "coords": [56.568796, 36.478926],
    "speed_kmh": 0,
    "current_task": "Укладка асфальтобетона",
    "location_type": "site",
    "location_name": "Участок М-11 км 78",
    "schedule": [
      {"date": "2026-05-18", "time": "08:00", "location": "Участок км 78", "task": "Прогрев и настройка"},
      {"date": "2026-05-18", "time": "08:30", "location": "Участок км 78", "task": "Укладка покрытия"},
      {"date": "2026-05-18", "time": "12:00", "location": "Участок км 78", "task": "Технологический перерыв"},
      {"date": "2026-05-18", "time": "13:00", "location": "Участок км 78", "task": "Укладка покрытия"},
      {"date": "2026-05-18", "time": "17:00", "location": "Участок км 78", "task": "Конец смены"}
    ]
  },
  {
    "id": 10,
    "type": "roller",
    "name": "Каток HAMM HD+ 120i №2",
    "home_type": "site",
    "home_id": "road-02",
    "coords": [56.568796, 36.478926],
    "speed_kmh": 0,
    "current_task": "Уплотнение покрытия",
    "location_type": "site",
    "location_name": "Участок М-11 км 78",
    "schedule": [
      {"date": "2026-05-18", "time": "08:30", "location": "Участок км 78", "task": "Уплотнение первичного слоя"},
      {"date": "2026-05-18", "time": "12:00", "location": "Участок км 78", "task": "Технологический перерыв"},
      {"date": "2026-05-18", "time": "13:00", "location": "Участок км 78", "task": "Уплотнение финишного слоя"},
      {"date": "2026-05-18", "time": "17:00", "location": "Участок км 78", "task": "Конец смены"}
    ]
  },
  {
    "id": 11,
    "type": "dump_truck",
    "name": "Самосвал Scania R500 №01",
    "home_type": "factory",
    "home_id": "abz_1_msk",
    "coords": [55.859778, 37.536148],
    "speed_kmh": 0,
    "current_task": "Загрузка на АБЗ",
    "location_type": "factory",
    "location_name": "АБЗ-1",
    "schedule": [
      {"date": "2026-05-18", "time": "07:00", "location": "АБЗ-1", "task": "Загрузка асфальтобетона"},
      {"date": "2026-05-18", "time": "09:00", "location": "Участок км 45", "task": "Разгрузка"},
      {"date": "2026-05-18", "time": "09:45", "location": "АБЗ-1", "task": "Обратный рейс"},
      {"date": "2026-05-18", "time": "11:45", "location": "Участок км 45", "task": "Разгрузка"},
      {"date": "2026-05-18", "time": "14:00", "location": "АБЗ-1", "task": "Конец смены"}
    ]
  },
  {
    "id": 12,
    "type": "dump_truck",
    "name": "Самосвал Scania R500 №02",
    "home_type": "factory",
    "home_id": "abz_1_msk",
    "coords": [55.859778, 37.536148],
    "speed_kmh": 0,
    "current_task": "Ожидание загрузки",
    "location_type": "factory",
    "location_name": "АБЗ-1",
    "schedule": [
      {"date": "2026-05-18", "time": "08:00", "location": "АБЗ-1", "task": "Загрузка асфальтобетона"},
      {"date": "2026-05-18", "time": "10:00", "location": "Участок км 78", "task": "Разгрузка"},
      {"date": "2026-05-18", "time": "11:00", "location": "АБЗ-1", "task": "Обратный рейс"},
      {"date": "2026-05-18", "time": "13:00", "location": "Участок км 78", "task": "Разгрузка"},
      {"date": "2026-05-18", "time": "15:00", "location": "АБЗ-1", "task": "Конец смены"}
    ]
  },
  {
    "id": 13,
    "type": "dump_truck",
    "name": "Самосвал КАМАЗ-65115 №01",
    "home_type": "factory",
    "home_id": "abz_likhoslavl",
    "coords": [57.129092, 35.434167],
    "speed_kmh": 0,
    "current_task": "Загрузка на АБЗ",
    "location_type": "factory",
    "location_name": "АБЗ (Лихославльский)",
    "schedule": [
      {"date": "2026-05-18", "time": "08:00", "location": "АБЗ Лихославльский", "task": "Загрузка асфальтобетона"},
      {"date": "2026-05-18", "time": "09:30", "location": "Участок км 112", "task": "Разгрузка"},
      {"date": "2026-05-18", "time": "10:30", "location": "АБЗ Лихославльский", "task": "Обратный рейс"},
      {"date": "2026-05-18", "time": "12:00", "location": "Участок км 112", "task": "Разгрузка"},
      {"date": "2026-05-18", "time": "14:00", "location": "АБЗ Лихославльский", "task": "Конец смены"}
    ]
  }
]
